loadcfg/__init__.py
loadcfg-0.1.1.dist-info/LICENSE
loadcfg-0.1.1.dist-info/METADATA
loadcfg-0.1.1.dist-info/WHEEL
loadcfg-0.1.1.dist-info/top_level.txt
loadcfg-0.1.1.dist-info/RECORD
