Metadata-Version: 2.2
Name: loadcfg
Version: 0.1.1
Summary: A configuration helper library for JSON and YAML config files with dot-access.
Home-page: https://github.com/danielkorkin/loadcfg
Author: Daniel Korkin
Author-email: daniel.d.korkin@gmail.com
License: MIT
Project-URL: Documentation, https://loadcfg.readthedocs.io
Project-URL: Code Coverage, https://app.codecov.io/gh/danielkorkin/loadcfg/
Project-URL: PyPI, https://pypi.org/project/loadcfg
Project-URL: Source, https://github.com/danielkorkin/loadcfg
Classifier: Development Status :: 3 - Alpha
Classifier: Intended Audience :: Developers
Classifier: License :: OSI Approved :: MIT License
Classifier: Programming Language :: Python :: 3
Classifier: Programming Language :: Python :: 3.6
Classifier: Programming Language :: Python :: 3.7
Classifier: Programming Language :: Python :: 3.8
Classifier: Programming Language :: Python :: 3.9
Classifier: Topic :: Software Development :: Libraries :: Python Modules
Requires-Python: >=3.6
License-File: LICENSE
Requires-Dist: PyYAML>=5.1
Requires-Dist: toml>=0.10.2
Provides-Extra: dev
Requires-Dist: pytest; extra == "dev"
Requires-Dist: pre-commit; extra == "dev"
Requires-Dist: black; extra == "dev"
Requires-Dist: isort; extra == "dev"
Requires-Dist: ruff; extra == "dev"
Requires-Dist: yamllint; extra == "dev"
Requires-Dist: pytest-cov; extra == "dev"
Requires-Dist: codecov; extra == "dev"
Dynamic: author
Dynamic: author-email
Dynamic: classifier
Dynamic: description
Dynamic: description-content-type
Dynamic: home-page
Dynamic: license
Dynamic: project-url
Dynamic: provides-extra
Dynamic: requires-dist
Dynamic: requires-python
Dynamic: summary
